{"1020":{"coordinates":[103.769317461,1.37347139841],"svy21":[20877.46,39497.1],"planningArea":"BP","neighbours":["BK","BT","CC","SK","CK"]},"1038":{"coordinates":[103.90265547,1.31177193188],"svy21":[35716.54,32674.7],"planningArea":"GL","neighbours":["BD","KL","HG","MP","TP"]},"1043":{"coordinates":[103.753682799,1.38355819427],"svy21":[19137.55,40612.5],"planningArea":"CK","neighbours":["BK","BP","SK","TH","WC"]},"1045":{"coordinates":[103.732974713,1.34868426521],"svy21":[16832.84,36756.4],"planningArea":"JE","neighbours":["BL","BK","JW","TH","CL","WI"]},"1071":{"coordinates":[103.807901836,1.29598798688],"svy21":[25171.34,30929.3],"planningArea":"QT","neighbours":["BM","BT","TN","CL"]},"1072":{"coordinates":[103.824179926,1.27496071054],"svy21":[26982.94,28604.2],"planningArea":"BM","neighbours":["QT","TN","SI","CA"]},"1073":{"coordinates":[103.80611768,1.33001920834],"svy21":[24972.82,34692.3],"planningArea":"BT","neighbours":["BK","BP","NV","QT","CC","TN","CL"]},"1077":{"coordinates":[103.87469321,1.37291571713],"svy21":[32604.49,39435.6],"planningArea":"SG","neighbours":["AM","BS","HG","SE","TP"]},"1102":{"coordinates":[103.921182039,1.33560042189],"svy21":[37778.28,35309.6],"planningArea":"BD","neighbours":["GL","HG","MP","PL","TM"]},"1107":{"coordinates":[103.73666945,1.33640316347],"svy21":[17243.97,35398.4],"planningArea":"JE","neighbours":["BL","BK","JW","TH","CL","WI"]},"1114":{"coordinates":[103.791771641,1.4367457091],"svy21":[23376.46,46493.6],"planningArea":"WD","neighbours":["MD","SB","SK"]},"1119":{"coordinates":[103.904303406,1.32441670248],"svy21":[35899.9,34072.9],"planningArea":"GL","neighbours":["BD","KL","HG","MP","TP"]},"1121":{"coordinates":[103.784141517,1.31684408693],"svy21":[22527.07,33235.5],"planningArea":"BT","neighbours":["BK","BP","NV","QT","CC","TN","CL"]},"1129":{"coordinates":[103.86535127,1.32220815441],"svy21":[31564.92,33828.6],"planningArea":"KL","neighbours":["GL","NV","MP","TP","CA"]},"1132":{"coordinates":[103.707578366,1.35148479234],"svy21":[14006.52,37066.2],"planningArea":"JW","neighbours":["BL","JE","PN","TH","WC"]},"1143":{"coordinates":[103.885430793,1.37779364467],"svy21":[33799.44,39975],"planningArea":"HG","neighbours":["BD","GL","PL","SE","SG","TP"]},"1145":{"coordinates":[103.808639192,1.27612995155],"svy21":[25253.38,28733.5],"planningArea":"BM","neighbours":["QT","TN","SI","CA"]},"1150":{"coordinates":[103.839041302,1.36909151374],"svy21":[28636.87,39012.7],"planningArea":"AM","neighbours":["BS","SE","SG","CC","YS"]},"1151":{"coordinates":[103.843165678,1.37639785908],"svy21":[29095.86,39820.6],"planningArea":"AM","neighbours":["BS","SE","SG","CC","YS"]},"1158":{"coordinates":[103.851032152,1.36519997541],"svy21":[29971.31,38582.4],"planningArea":"AM","neighbours":["BS","SE","SG","CC","YS"]},"1160":{"coordinates":[103.945982199,1.31780516049],"svy21":[40538.37,33342],"planningArea":"BD","neighbours":["GL","HG","MP","PL","TM"]},"1161":{"coordinates":[103.78577872,1.43269946932],"svy21":[22709.53,46046.2],"planningArea":"WD","neighbours":["MD","SB","SK"]},"1166":{"coordinates":[103.851810992,1.37189226497],"svy21":[30057.98,39322.4],"planningArea":"AM","neighbours":["BS","SE","SG","CC","YS"]},"1168":{"coordinates":[103.859059853,1.37171313348],"svy21":[30864.69,39302.6],"planningArea":"AM","neighbours":["BS","SE","SG","CC","YS"]},"1172":{"coordinates":[103.834027389,1.43349580595],"svy21":[28078.88,46134.2],"planningArea":"YS","neighbours":["AM","MD","SL","SB","SE","CC","SM"]},"1174":{"coordinates":[103.857012526,1.30374654896],"svy21":[30636.92,31787.2],"planningArea":"CA","neighbours":["BM","KL","MP","NV","TN"]},"1177":{"coordinates":[103.874100893,1.38997926673],"svy21":[32538.54,41322.4],"planningArea":"SE","neighbours":["AM","PR","HG","PL","PG","SL","SG","YS"]},"1183":{"coordinates":[103.919941459,1.32951952584],"svy21":[37640.24,34637.2],"planningArea":"BD","neighbours":["GL","HG","MP","PL","TM"]},"1189":{"coordinates":[103.853881202,1.36031457676],"svy21":[30288.38,38042.2],"planningArea":"AM","neighbours":["BS","SE","SG","CC","YS"]},"1195":{"coordinates":[103.719009813,1.34684417184],"svy21":[15278.69,36553],"planningArea":"JW","neighbours":["BL","JE","PN","TH","WC"]},"1197":{"coordinates":[103.757029952,1.31262092518],"svy21":[19509.8,32768.6],"planningArea":"CL","neighbours":["BK","BT","JE","QT"]},"1199":{"coordinates":[103.826148952,1.28449814949],"svy21":[27202.08,29658.8],"planningArea":"BM","neighbours":["QT","TN","SI","CA"]},"1201":{"coordinates":[103.943573024,1.35048623001],"svy21":[40270.09,36955.7],"planningArea":"TM","neighbours":["BD","PR","PL","CH"]},"1203":{"coordinates":[103.951225179,1.35059439215],"svy21":[41121.69,36967.7],"planningArea":"TM","neighbours":["BD","PR","PL","CH"]},"1205":{"coordinates":[103.890216306,1.35799610541],"svy21":[34332.06,37785.9],"planningArea":"HG","neighbours":["BD","GL","PL","SE","SG","TP"]},"1207":{"coordinates":[103.830480284,1.42764637911],"svy21":[27684.14,45487.4],"planningArea":"YS","neighbours":["AM","MD","SL","SB","SE","CC","SM"]},"1208":{"coordinates":[103.778270478,1.43064820397],"svy21":[21873.97,45819.4],"planningArea":"WD","neighbours":["MD","SB","SK"]},"1209":{"coordinates":[103.753588789,1.34594481107],"svy21":[19126.95,36453.4],"planningArea":"BK","neighbours":["BP","BT","JE","TH","CK","CL"]},"1211":{"coordinates":[103.876679917,1.33555730329],"svy21":[32825.66,35304.7],"planningArea":"TP","neighbours":["BS","GL","KL","NV","HG","SG","CC"]},"1212":{"coordinates":[103.923752601,1.31996840553],"svy21":[38064.42,33581.1],"planningArea":"BD","neighbours":["GL","HG","MP","PL","TM"]},"1217":{"coordinates":[103.83601888,1.29418300171],"svy21":[28300.52,30729.7],"planningArea":"CA","neighbours":["BM","KL","MP","NV","TN"]},"1218":{"coordinates":[103.911349074,1.33091343863],"svy21":[36683.99,34791.3],"planningArea":"BD","neighbours":["GL","HG","MP","PL","TM"]},"1219":{"coordinates":[103.950716095,1.35145898751],"svy21":[41065.03,37063.3],"planningArea":"TM","neighbours":["BD","PR","PL","CH"]},"1220":{"coordinates":[103.721557917,1.34756778095],"svy21":[15562.27,36633],"planningArea":"JW","neighbours":["BL","JE","PN","TH","WC"]},"1221":{"coordinates":[103.815228182,1.2859550269],"svy21":[25986.69,29819.9],"planningArea":"BM","neighbours":["QT","TN","SI","CA"]},"1222":{"coordinates":[103.948871896,1.35734828545],"svy21":[40859.76,37714.5],"planningArea":"TM","neighbours":["BD","PR","PL","CH"]},"1223":{"coordinates":[103.844209604,1.42699702178],"svy21":[29212.01,45415.6],"planningArea":"YS","neighbours":["AM","MD","SL","SB","SE","CC","SM"]},"1227":{"coordinates":[103.837908869,1.43368029167],"svy21":[28510.83,46154.6],"planningArea":"YS","neighbours":["AM","MD","SL","SB","SE","CC","SM"]},"1228":{"coordinates":[103.740999565,1.34919374139],"svy21":[17725.92,36812.7],"planningArea":"BK","neighbours":["BP","BT","JE","TH","CK","CL"]},"1229":{"coordinates":[103.748161475,1.35905880027],"svy21":[18523,37903.5],"planningArea":"BK","neighbours":["BP","BT","JE","TH","CK","CL"]},"1230":{"coordinates":[103.937745002,1.32399588735],"svy21":[39621.62,34026.5],"planningArea":"BD","neighbours":["GL","HG","MP","PL","TM"]},"1232":{"coordinates":[103.754210328,1.35415464392],"svy21":[19196.15,37361.2],"planningArea":"BK","neighbours":["BP","BT","JE","TH","CK","CL"]},"1234":{"coordinates":[103.844311132,1.32581675255],"svy21":[29223.36,34227.6],"planningArea":"NV","neighbours":["BT","KL","CC","TN","TP","CA"]},"1235":{"coordinates":[103.86976723,1.36019501195],"svy21":[32056.31,38029],"planningArea":"SG","neighbours":["AM","BS","HG","SE","TP"]},"1236":{"coordinates":[103.830299411,1.4174080754],"svy21":[27664.01,44355.3],"planningArea":"YS","neighbours":["AM","MD","SL","SB","SE","CC","SM"]},"1237":{"coordinates":[103.939546597,1.34696029953],"svy21":[39822.01,36565.8],"planningArea":"TM","neighbours":["BD","PR","PL","CH"]},"1238":{"coordinates":[103.756264456,1.34524492017],"svy21":[19424.72,36376],"planningArea":"BK","neighbours":["BP","BT","JE","TH","CK","CL"]},"1239":{"coordinates":[103.952183351,1.34020774171],"svy21":[41228.38,35819.2],"planningArea":"TM","neighbours":["BD","PR","PL","CH"]},"1240":{"coordinates":[103.769170735,1.37980194011],"svy21":[20861.15,40197.1],"planningArea":"BP","neighbours":["BK","BT","CC","SK","CK"]},"1241":{"coordinates":[103.747289776,1.3817664262],"svy21":[18426.08,40414.4],"planningArea":"CK","neighbours":["BK","BP","SK","TH","WC"]},"1242":{"coordinates":[103.955815888,1.37116930986],"svy21":[41632.47,39242.8],"planningArea":"PR","neighbours":["PL","PG","SE","CH","TM"]},"1243":{"coordinates":[103.962918865,1.37230842963],"svy21":[42422.94,39368.8],"planningArea":"PR","neighbours":["PL","PG","SE","CH","TM"]},"1244":{"coordinates":[103.741860477,1.37774271086],"svy21":[17821.85,39969.5],"planningArea":"CK","neighbours":["BK","BP","SK","TH","WC"]},"1245":{"coordinates":[103.767814621,1.38587289572],"svy21":[20710.25,40868.4],"planningArea":"BP","neighbours":["BK","BT","CC","SK","CK"]},"1246":{"coordinates":[103.850902652,1.31250356273],"svy21":[29956.94,32755.5],"planningArea":"KL","neighbours":["GL","NV","MP","TP","CA"]},"1247":{"coordinates":[103.766855272,1.33774986575],"svy21":[20603.34,35547.2],"planningArea":"BT","neighbours":["BK","BP","NV","QT","CC","TN","CL"]},"1248":{"coordinates":[103.718050458,1.3383756745],"svy21":[15171.88,35616.6],"planningArea":"JW","neighbours":["BL","JE","PN","TH","WC"]},"1249":{"coordinates":[103.773649748,1.38409868937],"svy21":[21359.62,40672.2],"planningArea":"BP","neighbours":["BK","BT","CC","SK","CK"]},"1250":{"coordinates":[103.79055697,1.42918430294],"svy21":[23241.27,45657.5],"planningArea":"WD","neighbours":["MD","SB","SK"]},"1251":{"coordinates":[103.912565882,1.39640197543],"svy21":[36819.17,42032.7],"planningArea":"PG","neighbours":["PR","SL","SE"]},"1252":{"coordinates":[103.817427238,1.45417583465],"svy21":[26231.55,48420.9],"planningArea":"SB","neighbours":["MD","WD","SM","YS"]},"1253":{"coordinates":[103.895854102,1.38289309908],"svy21":[34959.41,40538.9],"planningArea":"SE","neighbours":["AM","PR","HG","PL","PG","SL","SG","YS"]},"1254":{"coordinates":[103.887255995,1.39066179596],"svy21":[34002.53,41397.9],"planningArea":"SE","neighbours":["AM","PR","HG","PL","PG","SL","SG","YS"]},"1255":{"coordinates":[103.913071455,1.40000855862],"svy21":[36875.42,42431.5],"planningArea":"PG","neighbours":["PR","SL","SE"]},"1256":{"coordinates":[103.839996502,1.27560372173],"svy21":[28743.2,28675.3],"planningArea":"BM","neighbours":["QT","TN","SI","CA"]},"1257":{"coordinates":[103.699701741,1.33641298634],"svy21":[13129.847,35399.679],"planningArea":"JW","neighbours":["BL","JE","PN","TH","WC"]},"1258":{"coordinates":[103.700554939,1.34683352389],"svy21":[13224.8617,36551.9267],"planningArea":"JW","neighbours":["BL","JE","PN","TH","WC"]},"1259":{"coordinates":[103.898525408,1.4015109688],"svy21":[35256.6357,42597.579],"planningArea":"PG","neighbours":["PR","SL","SE"]},"1260":{"coordinates":[103.90546184,1.4049904847],"svy21":[36028.555,42982.3492],"planningArea":"PG","neighbours":["PR","SL","SE"]},"1261":{"coordinates":[103.874984872,1.39254008867],"svy21":[32636.9103,41605.5645],"planningArea":"SE","neighbours":["AM","PR","HG","PL","PG","SL","SG","YS"]},"1262":{"coordinates":[103.889611598,1.39475407759],"svy21":[34264.6671,41850.4101],"planningArea":"SE","neighbours":["AM","PR","HG","PL","PG","SL","SG","YS"]},"1263":{"coordinates":[103.891107732,1.38384505569],"svy21":[34431.1965,40644.1492],"planningArea":"SE","neighbours":["AM","PR","HG","PL","PG","SL","SG","YS"]},"1264":{"coordinates":[103.801831962,1.44704734186],"svy21":[24496.0361,47632.6851],"planningArea":"WD","neighbours":["MD","SB","SK"]},"1265":{"coordinates":[103.766310872,1.38949100476],"svy21":[20542.9133,41268.4771],"planningArea":"BP","neighbours":["BK","BT","CC","SK","CK"]},"1266":{"coordinates":[103.824119668,1.29133448213],"svy21":[26976.2403,30414.7271],"planningArea":"BM","neighbours":["QT","TN","SI","CA"]},"1267":{"coordinates":[103.813851258,1.4565632313],"svy21":[25833.6034,48684.8895],"planningArea":"SB","neighbours":["MD","WD","SM","YS"]},"1268":{"coordinates":[103.951673014,1.34857131133],"svy21":[41171.54,36744],"planningArea":"TM","neighbours":["BD","PR","PL","CH"]},"1269":{"coordinates":[103.89880462,1.41159891867],"svy21":[35287.6769,43713.0551],"planningArea":"PG","neighbours":["PR","SL","SE"]},"1270":{"coordinates":[103.911120072,1.40462338832],"svy21":[36658.2403,42941.7777],"planningArea":"PG","neighbours":["PR","SL","SE"]},"1271":{"coordinates":[103.918621581,1.39882800551],"svy21":[37493.0794,42300.982],"planningArea":"PG","neighbours":["PR","SL","SE"]},"1610":{"coordinates":[103.855667462,1.34052616414],"svy21":[30487.19,35854.1],"planningArea":"TP","neighbours":["BS","GL","KL","NV","HG","SG","CC"]},"1619":{"coordinates":[103.881619881,1.32453301028],"svy21":[33375.45,34085.7],"planningArea":"GL","neighbours":["BD","KL","HG","MP","TP"]},"1621":{"coordinates":[103.799964772,1.2998106436],"svy21":[24288.02,31352],"planningArea":"QT","neighbours":["BM","BT","TN","CL"]},"1640":{"coordinates":[103.712968991,1.34284659705],"svy21":[14606.39,36111],"planningArea":"JW","neighbours":["BL","JE","PN","TH","WC"]},"1645":{"coordinates":[103.77369771,1.43442290141],"svy21":[21365.1,46236.8],"planningArea":"WD","neighbours":["MD","SB","SK"]},"1650":{"coordinates":[103.767753508,1.31587061153],"svy21":[20703.24,33127.9],"planningArea":"CL","neighbours":["BK","BT","JE","QT"]},"1656":{"coordinates":[103.740918129,1.34272573208],"svy21":[17716.83,36097.5],"planningArea":"JE","neighbours":["BL","BK","JW","TH","CL","WI"]},"1657":{"coordinates":[103.931943564,1.33012951801],"svy21":[38975.95,34704.7],"planningArea":"BD","neighbours":["GL","HG","MP","PL","TM"]},"1658":{"coordinates":[103.932034018,1.33390342208],"svy21":[38986,35122],"planningArea":"BD","neighbours":["GL","HG","MP","PL","TM"]},"1724":{"coordinates":[103.883078286,1.37139622498],"svy21":[33537.65,39267.6],"planningArea":"HG","neighbours":["BD","GL","PL","SE","SG","TP"]},"1725":{"coordinates":[103.86836252,1.34897187276],"svy21":[31900,36788],"planningArea":"SG","neighbours":["AM","BS","HG","SE","TP"]},"1726":{"coordinates":[103.68783305,1.33895104061],"svy21":[11809,35680.4],"planningArea":"JW","neighbours":["BL","JE","PN","TH","WC"]},"1727":{"coordinates":[103.939646826,1.34789088455],"svy21":[39833.16,36668.7],"planningArea":"TM","neighbours":["BD","PR","PL","CH"]},"1729":{"coordinates":[103.840792869,1.42130316062],"svy21":[28831.78,44786],"planningArea":"YS","neighbours":["AM","MD","SL","SB","SE","CC","SM"]},"1730":{"coordinates":[103.838797628,1.41627942474],"svy21":[28609.74,44230.5],"planningArea":"YS","neighbours":["AM","MD","SL","SB","SE","CC","SM"]},"1731":{"coordinates":[103.687723924,1.34268423865],"svy21":[11796.88,36093.2],"planningArea":"JW","neighbours":["BL","JE","PN","TH","WC"]},"1734":{"coordinates":[103.78833971,1.4420352656],"svy21":[22994.55,47078.5],"planningArea":"WD","neighbours":["MD","SB","SK"]},"1735":{"coordinates":[103.849284669,1.34594787924],"svy21":[29776.85,36453.6],"planningArea":"BS","neighbours":["AM","SG","CC","TP"]},"1736":{"coordinates":[103.948936752,1.36069171056],"svy21":[40866.96,38084.2],"planningArea":"TM","neighbours":["BD","PR","PL","CH"]},"1737":{"coordinates":[103.945218619,1.37512280046],"svy21":[40453.1,39679.9],"planningArea":"PR","neighbours":["PL","PG","SE","CH","TM"]},"1738":{"coordinates":[103.832928947,1.43351841511],"svy21":[27956.64,46136.7],"planningArea":"YS","neighbours":["AM","MD","SL","SB","SE","CC","SM"]},"1740":{"coordinates":[103.848451413,1.42778198545],"svy21":[29684.06,45502.4],"planningArea":"YS","neighbours":["AM","MD","SL","SB","SE","CC","SM"]},"1741":{"coordinates":[103.695312457,1.34846717115],"svy21":[12641.44,36732.6],"planningArea":"JW","neighbours":["BL","JE","PN","TH","WC"]},"1742":{"coordinates":[103.894753317,1.37820038485],"svy21":[34836.92,40020],"planningArea":"HG","neighbours":["BD","GL","PL","SE","SG","TP"]},"1743":{"coordinates":[103.939688662,1.37777012437],"svy21":[39837.67,39972.6],"planningArea":"PR","neighbours":["PL","PG","SE","CH","TM"]},"1744":{"coordinates":[103.800114297,1.442679376],"svy21":[24304.88,47149.7],"planningArea":"WD","neighbours":["MD","SB","SK"]},"1745":{"coordinates":[103.74746537,1.39385957636],"svy21":[18445.67,41751.6],"planningArea":"CK","neighbours":["BK","BP","SK","TH","WC"]},"1746":{"coordinates":[103.899527831,1.38924977029],"svy21":[35368.23,41241.8],"planningArea":"SE","neighbours":["AM","PR","HG","PL","PG","SL","SG","YS"]},"1747":{"coordinates":[103.797841056,1.43476887325],"svy21":[24051.89,46275],"planningArea":"WD","neighbours":["MD","SB","SK"]},"1748":{"coordinates":[103.76028903,1.38359006091],"svy21":[19872.74,40616],"planningArea":"BP","neighbours":["BK","BT","CC","SK","CK"]},"1749":{"coordinates":[103.960948213,1.36551768169],"svy21":[42203.67,38617.9],"planningArea":"PR","neighbours":["PL","PG","SE","CH","TM"]},"1750":{"coordinates":[103.746993379,1.40282270105],"svy21":[18393.18,42742.7],"planningArea":"CK","neighbours":["BK","BP","SK","TH","WC"]},"1751":{"coordinates":[103.815639313,1.45090564249],"svy21":[26032.58,48059.3],"planningArea":"SB","neighbours":["MD","WD","SM","YS"]},"1752":{"coordinates":[103.904718232,1.39357337973],"svy21":[35945.84,41719.9],"planningArea":"SE","neighbours":["AM","PR","HG","PL","PG","SL","SG","YS"]},"1753":{"coordinates":[103.698743548,1.33971223624],"svy21":[13023.23,35764.5],"planningArea":"JW","neighbours":["BL","JE","PN","TH","WC"]},"1754":{"coordinates":[103.950947303,1.36832804896],"svy21":[41090.67,38928.6],"planningArea":"PR","neighbours":["PL","PG","SE","CH","TM"]},"1755":{"coordinates":[103.961797059,1.35304015256],"svy21":[42298.21,37238.2],"planningArea":"TM","neighbours":["BD","PR","PL","CH"]},"1756":{"coordinates":[103.794652868,1.44382692647],"svy21":[23697.11,47276.6],"planningArea":"WD","neighbours":["MD","SB","SK"]},"1757":{"coordinates":[103.898154677,1.3944309073],"svy21":[35215.4,41814.7],"planningArea":"SE","neighbours":["AM","PR","HG","PL","PG","SL","SG","YS"]},"1758":{"coordinates":[103.79038958,1.43305768891],"svy21":[23222.65,46085.8],"planningArea":"WD","neighbours":["MD","SB","SK"]},"1759":{"coordinates":[103.821021428,1.44504359318],"svy21":[26631.52,47411.1],"planningArea":"SB","neighbours":["MD","WD","SM","YS"]},"1760":{"coordinates":[103.736142755,1.380411258],"svy21":[17185.55,40264.6],"planningArea":"CK","neighbours":["BK","BP","SK","TH","WC"]},"1761":{"coordinates":[103.90351288,1.38752774654],"svy21":[35811.72,41051.4],"planningArea":"SE","neighbours":["AM","PR","HG","PL","PG","SL","SG","YS"]},"1762":{"coordinates":[103.751194543,1.39696077147],"svy21":[18860.69,42094.5],"planningArea":"CK","neighbours":["BK","BP","SK","TH","WC"]},"1763":{"coordinates":[103.88116617,1.37803972165],"svy21":[33324.84,40002.2],"planningArea":"HG","neighbours":["BD","GL","PL","SE","SG","TP"]},"1764":{"coordinates":[103.93514316,1.37597064222],"svy21":[39331.82,39773.6],"planningArea":"PR","neighbours":["PL","PG","SE","CH","TM"]},"1765":{"coordinates":[103.804629246,1.44011014079],"svy21":[24807.32,46865.6],"planningArea":"WD","neighbours":["MD","SB","SK"]},"1766":{"coordinates":[103.841238357,1.38466556378],"svy21":[28881.37,40734.8],"planningArea":"AM","neighbours":["BS","SE","SG","CC","YS"]},"1767":{"coordinates":[103.8223205,1.45193304223],"svy21":[26776.09,48172.9],"planningArea":"SB","neighbours":["MD","WD","SM","YS"]},"1769":{"coordinates":[103.907430442,1.40029723673],"svy21":[36247.65,42463.4],"planningArea":"PG","neighbours":["PR","SL","SE"]},"1770":{"coordinates":[103.698964141,1.34471156152],"svy21":[13047.81,36317.3],"planningArea":"JW","neighbours":["BL","JE","PN","TH","WC"]},"1771":{"coordinates":[103.957291241,1.37278894605],"svy21":[41796.65,39421.9],"planningArea":"PR","neighbours":["PL","PG","SE","CH","TM"]},"1772":{"coordinates":[103.76329778,1.31581351471],"svy21":[20207.36,33121.6],"planningArea":"CL","neighbours":["BK","BT","JE","QT"]},"1773":{"coordinates":[103.900531668,1.30530669112],"svy21":[35480.2,31959.8],"planningArea":"MP","neighbours":["BD","GL","KL","CA"]},"3001":{"coordinates":[103.851554107068,1.37434001701182],"svy21":[30029.3897069506,39593.0597646125],"planningArea":"AM","neighbours":["BS","SE","SG","CC","YS"]},"3002":{"coordinates":[103.882806211705,1.33995415587812],"svy21":[33507.4424001062,35790.894505281],"planningArea":"TP","neighbours":["BS","GL","KL","NV","HG","SG","CC"]},"3003":{"coordinates":[103.852285636587,1.34177065550556],"svy21":[30110.8281688485,35991.7063233368],"planningArea":"TP","neighbours":["BS","GL","KL","NV","HG","SG","CC"]},"3004":{"coordinates":[103.87393306407,1.33375800216337],"svy21":[32519.9674407803,35105.7372267023],"planningArea":"TP","neighbours":["BS","GL","KL","NV","HG","SG","CC"]},"3005":{"coordinates":[103.817544461483,1.29331947049732],"svy21":[26244.4775615549,30634.2204785496],"planningArea":"BM","neighbours":["QT","TN","SI","CA"]},"3006":{"coordinates":[103.823733672546,1.289071144584],"svy21":[26933.2812846676,30164.4590708911],"planningArea":"BM","neighbours":["QT","TN","SI","CA"]},"3007":{"coordinates":[103.802207291626,1.30022271592191],"svy21":[24537.5928928247,31397.5616540778],"planningArea":"QT","neighbours":["BM","BT","TN","CL"]},"3008":{"coordinates":[103.828959585733,1.31169502827792],"svy21":[27514.8853741372,32666.0899762101],"planningArea":"CA","neighbours":["BM","KL","MP","NV","TN"]},"3009":{"coordinates":[103.845875101829,1.34618776148598],"svy21":[29397.4025306292,36480.1227368657],"planningArea":"BS","neighbours":["AM","SG","CC","TP"]},"3010":{"coordinates":[103.902138740699,1.37465538827444],"svy21":[35658.8371386677,39628.0344803333],"planningArea":"HG","neighbours":["BD","GL","PL","SE","SG","TP"]},"3012":{"coordinates":[103.745637393049,1.31920395934804],"svy21":[18241.9409345528,33496.5605151374],"planningArea":"JE","neighbours":["BL","BK","JW","TH","CL","WI"]},"3013":{"coordinates":[103.927030801519,1.322039120111],"svy21":[38429.2432294674,33810.0827980973],"planningArea":"BD","neighbours":["GL","HG","MP","PL","TM"]},"3014":{"coordinates":[103.927980967183,1.30871302488523],"svy21":[38535.0432412764,32336.5536597651],"planningArea":"BD","neighbours":["GL","HG","MP","PL","TM"]},"3015":{"coordinates":[103.842552378136,1.35505208480652],"svy21":[29027.6163034569,37460.2926999293],"planningArea":"BS","neighbours":["AM","SG","CC","TP"]},"3019":{"coordinates":[103.722687235839,1.34718626876969],"svy21":[15687.9488993771,36590.808515802],"planningArea":"JW","neighbours":["BL","JE","PN","TH","WC"]},"3020":{"coordinates":[103.828764316679,1.4281332427609],"svy21":[27493.1783263981,45541.2352395412],"planningArea":"YS","neighbours":["AM","MD","SL","SB","SE","CC","SM"]},"3021":{"coordinates":[103.860634248131,1.32425869967176],"svy21":[31039.9597734809,34055.3325261809],"planningArea":"KL","neighbours":["GL","NV","MP","TP","CA"]},"3024":{"coordinates":[103.777625748539,1.430704528838],"svy21":[21802.2213575505,45825.629854802],"planningArea":"WD","neighbours":["MD","SB","SK"]},"3026":{"coordinates":[103.842154973672,1.36733710171073],"svy21":[28983.3847605428,38818.7070966084],"planningArea":"AM","neighbours":["BS","SE","SG","CC","YS"]},"3027":{"coordinates":[103.950989139261,1.32513655159184],"svy21":[41095.5563319363,34152.6950651165],"planningArea":"BD","neighbours":["GL","HG","MP","PL","TM"]},"3029":{"coordinates":[103.762020598796,1.31553912917703],"svy21":[20065.2210741322,33091.2638591994],"planningArea":"CL","neighbours":["BK","BT","JE","QT"]},"3030":{"coordinates":[103.947564112294,1.31591673150617],"svy21":[40714.4314153828,33133.1948234756],"planningArea":"BD","neighbours":["GL","HG","MP","PL","TM"]},"3031":{"coordinates":[103.835360726863,1.36827266209724],"svy21":[28227.266494506,38922.1548925973],"planningArea":"AM","neighbours":["BS","SE","SG","CC","YS"]},"3033":{"coordinates":[103.910702097218,1.33467855511563],"svy21":[36611.9750076178,35207.6254042946],"planningArea":"BD","neighbours":["GL","HG","MP","PL","TM"]},"3037":{"coordinates":[103.944263709507,1.34926094811198],"svy21":[40346.9617786119,36820.2178275548],"planningArea":"TM","neighbours":["BD","PR","PL","CH"]},"3040":{"coordinates":[103.752226593984,1.34573305542943],"svy21":[18975.3516749172,36429.9901175778],"planningArea":"BK","neighbours":["BP","BT","JE","TH","CK","CL"]},"3041":{"coordinates":[103.774586410437,1.43912528141358],"svy21":[21464.012295194,46756.7632628046],"planningArea":"WD","neighbours":["MD","SB","SK"]},"3043":{"coordinates":[103.877659577677,1.37035994436211],"svy21":[32934.6156324316,39153.0014795568],"planningArea":"HG","neighbours":["BD","GL","PL","SE","SG","TP"]},"3044":{"coordinates":[103.740873704829,1.34849085621929],"svy21":[17711.9101901278,36734.978978157],"planningArea":"BK","neighbours":["BP","BT","JE","TH","CK","CL"]},"3045":{"coordinates":[103.838094226361,1.43232156717387],"svy21":[28531.4577029096,46004.3591205142],"planningArea":"YS","neighbours":["AM","MD","SL","SB","SE","CC","SM"]},"3046":{"coordinates":[103.882533963338,1.37764019332166],"svy21":[33477.0592164434,39958.0252705533],"planningArea":"HG","neighbours":["BD","GL","PL","SE","SG","TP"]},"3047":{"coordinates":[103.768561208485,1.30809499133647],"svy21":[20793.1069994289,32268.1090011336],"planningArea":"CL","neighbours":["BK","BT","JE","QT"]},"3048":{"coordinates":[103.752986488399,1.35273576615915],"svy21":[19059.945210902,37204.3120635785],"planningArea":"BK","neighbours":["BP","BT","JE","TH","CK","CL"]},"3049":{"coordinates":[103.956944585725,1.36658417167241],"svy21":[41758.1067258874,38735.8040275145],"planningArea":"PR","neighbours":["PL","PG","SE","CH","TM"]},"3050":{"coordinates":[103.88305161385,1.37255884700005],"svy21":[33534.6789847184,39396.1568145081],"planningArea":"HG","neighbours":["BD","GL","PL","SE","SG","TP"]},"3051":{"coordinates":[103.773828466913,1.38186433722815],"svy21":[21379.5029344717,40425.1360503435],"planningArea":"BP","neighbours":["BK","BT","CC","SK","CK"]},"3053":{"coordinates":[103.930354460965,1.34957303526222],"svy21":[38799.013808093,36854.6607348025],"planningArea":"TM","neighbours":["BD","PR","PL","CH"]},"3054":{"coordinates":[103.8329678742,1.36491023791199],"svy21":[27960.9707411807,38550.3550575394],"planningArea":"BS","neighbours":["AM","SG","CC","TP"]},"3055":{"coordinates":[103.751878290333,1.38319029263489],"svy21":[18936.72948555,40571.8260801993],"planningArea":"CK","neighbours":["BK","BP","SK","TH","WC"]},"3056":{"coordinates":[103.927091653438,1.33692798510395],"svy21":[38435.9529452939,35456.4196343441],"planningArea":"BD","neighbours":["GL","HG","MP","PL","TM"]},"3057":{"coordinates":[103.85801093879,1.36363517582632],"svy21":[30747.9677732345,38409.379259795],"planningArea":"AM","neighbours":["BS","SE","SG","CC","YS"]},"3058":{"coordinates":[103.840104687784,1.43580183362641],"svy21":[28755.1906478005,46389.1900489945],"planningArea":"YS","neighbours":["AM","MD","SL","SB","SE","CC","SM"]},"3059":{"coordinates":[103.962762942764,1.36933055696638],"svy21":[42405.605487165,39039.5202101804],"planningArea":"PR","neighbours":["PL","PG","SE","CH","TM"]},"3060":{"coordinates":[103.726657927977,1.35204084505868],"svy21":[16129.8673033705,37127.5839961097],"planningArea":"JW","neighbours":["BL","JE","PN","TH","WC"]},"3061":{"coordinates":[103.83021606804,1.36665944653815],"svy21":[27654.7276661601,38743.7738600392],"planningArea":"BS","neighbours":["AM","SG","CC","TP"]},"3063":{"coordinates":[103.728907710089,1.35128862770287],"svy21":[16380.2394942148,37044.3966198452],"planningArea":"JE","neighbours":["BL","BK","JW","TH","CL","WI"]},"3064":{"coordinates":[103.770799892647,1.36890870244512],"svy21":[21042.4232613929,38992.5756268147],"planningArea":"BP","neighbours":["BK","BT","CC","SK","CK"]},"3065":{"coordinates":[103.756493446009,1.38169398994364],"svy21":[19450.3327055648,40406.355250733],"planningArea":"CK","neighbours":["BK","BP","SK","TH","WC"]},"3066":{"coordinates":[103.687310264575,1.33872277341331],"svy21":[11750.8178531472,35655.1627567858],"planningArea":"JW","neighbours":["BL","JE","PN","TH","WC"]},"3067":{"coordinates":[103.7601288271,1.38782283796462],"svy21":[19854.9258730253,41084.0399392247],"planningArea":"BP","neighbours":["BK","BT","CC","SK","CK"]},"3068":{"coordinates":[103.702098132307,1.33525634519939],"svy21":[13396.5338022439,35271.7688311022],"planningArea":"JW","neighbours":["BL","JE","PN","TH","WC"]},"3069":{"coordinates":[103.935028383346,1.33451947288433],"svy21":[39319.2390878526,35190.1334154326],"planningArea":"BD","neighbours":["GL","HG","MP","PL","TM"]},"3070":{"coordinates":[103.909213706482,1.40205738421401],"svy21":[36446.096982968,42658.0347204506],"planningArea":"PG","neighbours":["PR","SL","SE"]},"3071":{"coordinates":[103.899188813886,1.38113128535803],"svy21":[35330.5266452953,40344.0974890459],"planningArea":"SE","neighbours":["AM","PR","HG","PL","PG","SL","SG","YS"]},"3072":{"coordinates":[103.802398196596,1.44589068910993],"svy21":[24559.0472937031,47504.7873554397],"planningArea":"WD","neighbours":["MD","SB","SK"]},"3073":{"coordinates":[103.878457896556,1.39033340759784],"svy21":[33023.4169629766,41361.5679294318],"planningArea":"SE","neighbours":["AM","PR","HG","PL","PG","SL","SG","YS"]},"3074":{"coordinates":[103.91170014084,1.39696019909524],"svy21":[36722.8223570511,42094.4223745242],"planningArea":"PG","neighbours":["PR","SL","SE"]},"3075":{"coordinates":[103.902687385465,1.40059309981827],"svy21":[35719.8105087355,42496.0989190731],"planningArea":"PG","neighbours":["PR","SL","SE"]},"3076":{"coordinates":[103.948972483629,1.36724684974879],"svy21":[40870.9016361376,38809.0355677698],"planningArea":"PR","neighbours":["PL","PG","SE","CH","TM"]},"3101":{"coordinates":[103.882941559613,1.29996190284073],"svy21":[33522.593372304,31368.7551599536],"planningArea":"KL","neighbours":["GL","NV","MP","TP","CA"]},"3103":{"coordinates":[103.709022155892,1.34407801177096],"svy21":[14167.1560925944,36247.1858429499],"planningArea":"JW","neighbours":["BL","JE","PN","TH","WC"]},"3201":{"coordinates":[103.829715264944,1.43606162738281],"svy21":[27599.0061242161,46417.9159394763],"planningArea":"YS","neighbours":["AM","MD","SL","SB","SE","CC","SM"]},"3202":{"coordinates":[103.886917440944,1.30705051215339],"svy21":[33965.0568118803,32152.5864589345],"planningArea":"GL","neighbours":["BD","KL","HG","MP","TP"]},"3203":{"coordinates":[103.813023119574,1.28578413756165],"svy21":[25741.2847723961,29801.0057836827],"planningArea":"BM","neighbours":["QT","TN","SI","CA"]},"3204":{"coordinates":[103.738353880163,1.38222557166114],"svy21":[17431.6287214421,40465.2079247907],"planningArea":"CK","neighbours":["BK","BP","SK","TH","WC"]},"3207":{"coordinates":[103.956213320582,1.36065258559016],"svy21":[41676.7589468686,38079.9137704317],"planningArea":"TM","neighbours":["BD","PR","PL","CH"]},"3211":{"coordinates":[103.723952961648,1.33002032220944],"svy21":[15828.7257759338,34692.6761670448],"planningArea":"JW","neighbours":["BL","JE","PN","TH","WC"]},"3214":{"coordinates":[103.831050390247,1.41937881620446],"svy21":[27747.5833931249,44573.2144819256],"planningArea":"YS","neighbours":["AM","MD","SL","SB","SE","CC","SM"]},"3215":{"coordinates":[103.83712733566,1.28651406161832],"svy21":[28423.8826554641,29881.7083400935],"planningArea":"CA","neighbours":["BM","KL","MP","NV","TN"]},"3222":{"coordinates":[103.84213696352,1.37797597740928],"svy21":[28981.3761166073,39995.0998579133],"planningArea":"AM","neighbours":["BS","SE","SG","CC","YS"]},"3223":{"coordinates":[103.72089870437,1.3420063576447],"svy21":[15488.878398424,36018.0484284945],"planningArea":"JW","neighbours":["BL","JE","PN","TH","WC"]},"3224":{"coordinates":[103.701890026285,1.34272269102177],"svy21":[13373.4179917388,36097.3625622243],"planningArea":"JW","neighbours":["BL","JE","PN","TH","WC"]},"3225":{"coordinates":[103.943776244752,1.32415704057062],"svy21":[40292.8371149516,34044.3486078382],"planningArea":"BD","neighbours":["GL","HG","MP","PL","TM"]},"3226":{"coordinates":[103.721832319897,1.35234365488343],"svy21":[15592.832184297,37161.0913502499],"planningArea":"JW","neighbours":["BL","JE","PN","TH","WC"]},"3228":{"coordinates":[103.852547896858,1.36599823336935],"svy21":[30139.9936715271,38670.66859781],"planningArea":"AM","neighbours":["BS","SE","SG","CC","YS"]},"3231":{"coordinates":[103.920700671715,1.327016727265],"svy21":[37724.7424391946,34360.4560187515],"planningArea":"BD","neighbours":["GL","HG","MP","PL","TM"]},"3232":{"coordinates":[103.870010748511,1.35951583249591],"svy21":[32083.4118273379,37953.900193736],"planningArea":"SG","neighbours":["AM","BS","HG","SE","TP"]},"3234":{"coordinates":[103.739894448684,1.34015604992645],"svy21":[17602.8944774615,35813.361642627],"planningArea":"JE","neighbours":["BL","BK","JW","TH","CL","WI"]},"3235":{"coordinates":[103.948962626204,1.35422732653399],"svy21":[40869.8736143382,37369.4000635855],"planningArea":"TM","neighbours":["BD","PR","PL","CH"]},"3237":{"coordinates":[103.949587247577,1.35826175936646],"svy21":[40939.3655754747,37815.5113097541],"planningArea":"TM","neighbours":["BD","PR","PL","CH"]},"3238":{"coordinates":[103.850208933898,1.34440856015541],"svy21":[29879.7116217427,36283.3906495292],"planningArea":"BS","neighbours":["AM","SG","CC","TP"]},"3239":{"coordinates":[103.788313471813,1.44107794946846],"svy21":[22991.6278989911,46972.6448137909],"planningArea":"WD","neighbours":["MD","SB","SK"]},"3240":{"coordinates":[103.869430481414,1.34840720846211],"svy21":[32018.8531237962,36725.5640310179],"planningArea":"SG","neighbours":["AM","BS","HG","SE","TP"]},"3304":{"coordinates":[103.750396136688,1.36471742697479],"svy21":[18771.713583881,38529.1941047646],"planningArea":"BK","neighbours":["BP","BT","JE","TH","CK","CL"]},"3307":{"coordinates":[103.760032628302,1.34233921440626],"svy21":[19844.0669009183,36054.6887308247],"planningArea":"BK","neighbours":["BP","BT","JE","TH","CK","CL"]},"3402":{"coordinates":[103.953245525564,1.33950630072878],"svy21":[41346.5926023424,35741.6438345034],"planningArea":"TM","neighbours":["BD","PR","PL","CH"]},"3403":{"coordinates":[103.755330021114,1.3830891794707],"svy21":[19320.8631910253,40560.6325863358],"planningArea":"CK","neighbours":["BK","BP","SK","TH","WC"]},"3503":{"coordinates":[103.709804106175,1.34185171197924],"svy21":[14254.1663757386,36001.008007681],"planningArea":"JW","neighbours":["BL","JE","PN","TH","WC"]},"3507":{"coordinates":[103.77318863421,1.30977590011361],"svy21":[21308.1010938305,32453.9625329766],"planningArea":"QT","neighbours":["BM","BT","TN","CL"]},"3508":{"coordinates":[103.813190980055,1.29352126774655],"svy21":[25759.9730125107,30656.5376077686],"planningArea":"QT","neighbours":["BM","BT","TN","CL"]},"3509":{"coordinates":[103.869270301748,1.3693257049095],"svy21":[32000.9925011601,39038.6248832233],"planningArea":"SG","neighbours":["AM","BS","HG","SE","TP"]},"3511":{"coordinates":[103.758158358303,1.30970169234126],"svy21":[19635.3712416785,32445.8021634948],"planningArea":"CL","neighbours":["BK","BT","JE","QT"]},"3512":{"coordinates":[103.897225195927,1.30873515818477],"svy21":[35112.2101560915,32338.8928906191],"planningArea":"MP","neighbours":["BD","GL","KL","CA"]},"3604":{"coordinates":[103.800148469692,1.43648894729943],"svy21":[24308.672863028,46465.1933193244],"planningArea":"WD","neighbours":["MD","SB","SK"]},"3605":{"coordinates":[103.837859241343,1.4153203280701],"svy21":[28505.3110986594,44124.4477044716],"planningArea":"YS","neighbours":["AM","MD","SL","SB","SE","CC","SM"]},"3606":{"coordinates":[103.81684325839,1.4453150213139],"svy21":[26166.5553313252,47441.1161091812],"planningArea":"SB","neighbours":["MD","WD","SM","YS"]},"3607":{"coordinates":[103.898365036709,1.38659683143748],"svy21":[35238.8340261411,40948.4476958662],"planningArea":"SE","neighbours":["AM","PR","HG","PL","PG","SL","SG","YS"]},"3608":{"coordinates":[103.933886165824,1.35361315263539],"svy21":[39192.035162162,37301.4129357953],"planningArea":"TM","neighbours":["BD","PR","PL","CH"]},"3609":{"coordinates":[103.960640700026,1.3562250904733],"svy21":[42169.5015027728,37590.3682703059],"planningArea":"TM","neighbours":["BD","PR","PL","CH"]},"3611":{"coordinates":[103.746025843729,1.40002893292858],"svy21":[18285.4948681146,42433.7828915156],"planningArea":"CK","neighbours":["BK","BP","SK","TH","WC"]},"3612":{"coordinates":[103.845147332528,1.42081285020657],"svy21":[29316.368751674,44731.7859666459],"planningArea":"YS","neighbours":["AM","MD","SL","SB","SE","CC","SM"]},"3613":{"coordinates":[103.959728202919,1.37284060102249],"svy21":[42067.8542885985,39427.6259528901],"planningArea":"PR","neighbours":["PL","PG","SE","CH","TM"]},"3614":{"coordinates":[103.72652089832,1.3470140891376],"svy21":[16114.5930194072,36571.7507036068],"planningArea":"JW","neighbours":["BL","JE","PN","TH","WC"]},"3615":{"coordinates":[103.776008090182,1.43664424769958],"svy21":[21622.2165687364,46482.418859126],"planningArea":"WD","neighbours":["MD","SB","SK"]},"3616":{"coordinates":[103.79604758539,1.42831828137014],"svy21":[23852.2922348073,45561.7290254198],"planningArea":"WD","neighbours":["MD","SB","SK"]},"3617":{"coordinates":[103.76552155794,1.38836870373382],"svy21":[20455.069193325,41144.3811624516],"planningArea":"BP","neighbours":["BK","BT","CC","SK","CK"]},"3618":{"coordinates":[103.751034411529,1.39327908335685],"svy21":[18842.8552409336,41687.3977799304],"planningArea":"CK","neighbours":["BK","BP","SK","TH","WC"]},"3619":{"coordinates":[103.764889617566,1.301227734261],"svy21":[20384.4722389067,31508.7733694986],"planningArea":"CL","neighbours":["BK","BT","JE","QT"]},"3620":{"coordinates":[103.701772102139,1.35373698510995],"svy21":[13360.3600808838,37315.2708597276],"planningArea":"JW","neighbours":["BL","JE","PN","TH","WC"]},"3621":{"coordinates":[103.814194898113,1.45322492445716],"svy21":[25871.8417550549,48315.7558995113],"planningArea":"SB","neighbours":["MD","WD","SM","YS"]},"3622":{"coordinates":[103.899847164494,1.39614083952012],"svy21":[35403.7461086269,42003.7810229808],"planningArea":"SE","neighbours":["AM","PR","HG","PL","PG","SL","SG","YS"]},"3623":{"coordinates":[103.794137756171,1.4414913127374],"svy21":[23639.7815383635,47018.3404796124],"planningArea":"WD","neighbours":["MD","SB","SK"]},"5001":{"coordinates":[103.841287803,1.30908420911],"svy21":[28886.9,32377.4],"planningArea":"CA","neighbours":["BM","KL","MP","NV","TN"]},"5003":{"coordinates":[103.881692253,1.3265126623],"svy21":[33383.5,34304.6],"planningArea":"GL","neighbours":["BD","KL","HG","MP","TP"]},"5004":{"coordinates":[103.841918306,1.33281744828],"svy21":[28957.06,35001.7],"planningArea":"TP","neighbours":["BS","GL","KL","NV","HG","SG","CC"]},"5005":{"coordinates":[103.82806951,1.27484405842],"svy21":[27415.82,28591.3],"planningArea":"BM","neighbours":["QT","TN","SI","CA"]},"5007":{"coordinates":[103.897659347,1.37317385438],"svy21":[35160.34,39464.2],"planningArea":"HG","neighbours":["BD","GL","PL","SE","SG","TP"]},"5008":{"coordinates":[103.743443557,1.39507127173],"svy21":[17998.1,41885.6],"planningArea":"CK","neighbours":["BK","BP","SK","TH","WC"]},"5009":{"coordinates":[103.865128906,1.331388361],"svy21":[31540.16,34843.7],"planningArea":"TP","neighbours":["BS","GL","KL","NV","HG","SG","CC"]},"5011":{"coordinates":[103.941344805,1.33486527073],"svy21":[40022.19,35228.4],"planningArea":"BD","neighbours":["GL","HG","MP","PL","TM"]},"5012":{"coordinates":[103.862332001,1.34933731578],"svy21":[31228.87,36828.4],"planningArea":"SG","neighbours":["AM","BS","HG","SE","TP"]},"5013":{"coordinates":[103.846277773,1.3037755672],"svy21":[29442.24,31790.4],"planningArea":"CA","neighbours":["BM","KL","MP","NV","TN"]},"5014":{"coordinates":[103.845794784,1.31768650752],"svy21":[29388.48,33328.6],"planningArea":"NV","neighbours":["BT","KL","CC","TN","TP","CA"]},"5015":{"coordinates":[103.917375278,1.31889695967],"svy21":[37354.69,33462.6],"planningArea":"BD","neighbours":["GL","HG","MP","PL","TM"]},"5017":{"coordinates":[103.864250093,1.35795136175],"svy21":[31442.32,37780.9],"planningArea":"SG","neighbours":["AM","BS","HG","SE","TP"]},"5018":{"coordinates":[103.889690747,1.37393733985],"svy21":[34273.53,39548.6],"planningArea":"HG","neighbours":["BD","GL","PL","SE","SG","TP"]},"5019":{"coordinates":[103.767694735,1.3667573581],"svy21":[20696.85,38754.7],"planningArea":"BP","neighbours":["BK","BT","CC","SK","CK"]},"5020":{"coordinates":[103.785692179,1.30079797926],"svy21":[22699.61,31461.2],"planningArea":"QT","neighbours":["BM","BT","TN","CL"]},"5022":{"coordinates":[103.883964248,1.31765708146],"svy21":[33636.37,33325.4],"planningArea":"GL","neighbours":["BD","KL","HG","MP","TP"]},"5024":{"coordinates":[103.855170727,1.34938351366],"svy21":[30431.9,36833.5],"planningArea":"BS","neighbours":["AM","SG","CC","TP"]},"5025":{"coordinates":[103.936787221,1.3494067208],"svy21":[39514.91,36836.3],"planningArea":"TM","neighbours":["BD","PR","PL","CH"]},"5026":{"coordinates":[103.827976504,1.32109056166],"svy21":[27405.48,33705],"planningArea":"NV","neighbours":["BT","KL","CC","TN","TP","CA"]},"5027":{"coordinates":[103.783438978,1.33293994829],"svy21":[22448.92,35015.3],"planningArea":"BT","neighbours":["BK","BP","NV","QT","CC","TN","CL"]},"5028":{"coordinates":[103.890924922,1.39206437679],"svy21":[34410.83,41553],"planningArea":"SE","neighbours":["AM","PR","HG","PL","PG","SL","SG","YS"]},"5168":{"coordinates":[103.888209399,1.31111391543],"svy21":[34108.83,32601.9],"planningArea":"GL","neighbours":["BD","KL","HG","MP","TP"]},"5183":{"coordinates":[103.908572544,1.39480500186],"svy21":[36374.77,41856.1],"planningArea":"PG","neighbours":["PR","SL","SE"]},"5197":{"coordinates":[103.917769916,1.30530978558],"svy21":[37398.66,31960.2],"planningArea":"MP","neighbours":["BD","GL","KL","CA"]},"5214":{"coordinates":[103.934546719,1.33339144984],"svy21":[39265.64,35065.4],"planningArea":"BD","neighbours":["GL","HG","MP","PL","TM"]},"5240":{"coordinates":[103.911204219,1.30463082149],"svy21":[36667.96,31885.1],"planningArea":"MP","neighbours":["BD","GL","KL","CA"]},"5258":{"coordinates":[103.808122539,1.32095387972],"svy21":[25195.93,33689.9],"planningArea":"BT","neighbours":["BK","BP","NV","QT","CC","TN","CL"]},"5259":{"coordinates":[103.749294014,1.36463876218],"svy21":[18649.06,38520.5],"planningArea":"BK","neighbours":["BP","BT","JE","TH","CK","CL"]},"5601":{"coordinates":[103.901527615,1.32840683472],"svy21":[35590.97,34514.1],"planningArea":"GL","neighbours":["BD","KL","HG","MP","TP"]},"5602":{"coordinates":[103.855473433,1.33728854118],"svy21":[30465.6,35496.1],"planningArea":"TP","neighbours":["BS","GL","KL","NV","HG","SG","CC"]},"5603":{"coordinates":[103.935352491,1.35808685753],"svy21":[39355.2,37796.1],"planningArea":"TM","neighbours":["BD","PR","PL","CH"]},"5608":{"coordinates":[103.847761108,1.33740707074],"svy21":[29607.3,35509.2],"planningArea":"TP","neighbours":["BS","GL","KL","NV","HG","SG","CC"]},"5622":{"coordinates":[103.761612083,1.31955120277],"svy21":[20019.77,33534.9],"planningArea":"CL","neighbours":["BK","BT","JE","QT"]},"5623":{"coordinates":[103.776108167,1.33805487114],"svy21":[21633.09,35580.9],"planningArea":"BT","neighbours":["BK","BP","NV","QT","CC","TN","CL"]},"5625":{"coordinates":[103.832707014,1.36088984044],"svy21":[27931.94,38105.8],"planningArea":"BS","neighbours":["AM","SG","CC","TP"]},"5626":{"coordinates":[103.857651746,1.32168913706],"svy21":[30708.04,33771.2],"planningArea":"KL","neighbours":["GL","NV","MP","TP","CA"]},"5634":{"coordinates":[103.893684087,1.36673760166],"svy21":[34717.96,38752.5],"planningArea":"HG","neighbours":["BD","GL","PL","SE","SG","TP"]},"5635":{"coordinates":[103.884978304,1.34984157321],"svy21":[33749.15,36884.2],"planningArea":"HG","neighbours":["BD","GL","PL","SE","SG","TP"]},"5636":{"coordinates":[103.839070674,1.43846166028],"svy21":[28640.12,46683.3],"planningArea":"YS","neighbours":["AM","MD","SL","SB","SE","CC","SM"]},"5637":{"coordinates":[103.910921505,1.30652637707],"svy21":[36636.49,32094.7],"planningArea":"BD","neighbours":["GL","HG","MP","PL","TM"]},"5638":{"coordinates":[103.835345082,1.31871841816],"svy21":[28225.53,33442.7],"planningArea":"NV","neighbours":["BT","KL","CC","TN","TP","CA"]},"7001":{"coordinates":[103.780363417671,1.30370409257786],"svy21":[22106.5732889473,31782.5550005585],"planningArea":"QT","neighbours":["BM","BT","TN","CL"]},"7002":{"coordinates":[103.766687526556,1.36838160662859],"svy21":[20584.7646280946,38934.3043401893],"planningArea":"BP","neighbours":["BK","BT","CC","SK","CK"]},"7004":{"coordinates":[103.843271625083,1.33246079948306],"svy21":[29107.6704288516,34962.2641689591],"planningArea":"TP","neighbours":["BS","GL","KL","NV","HG","SG","CC"]},"7005":{"coordinates":[103.882673394367,1.31767083360151],"svy21":[33492.7104578754,33326.9177586734],"planningArea":"GL","neighbours":["BD","KL","HG","MP","TP"]},"7008":{"coordinates":[103.91714436743,1.30644253773365],"svy21":[37329.037949441,32085.4517078344],"planningArea":"MP","neighbours":["BD","GL","KL","CA"]},"7011":{"coordinates":[103.888928609198,1.37396126564932],"svy21":[34188.7133301115,39551.2436067984],"planningArea":"HG","neighbours":["BD","GL","PL","SE","SG","TP"]},"7014":{"coordinates":[103.828192119961,1.32104508236811],"svy21":[27429.4758435786,33699.9710817412],"planningArea":"NV","neighbours":["BT","KL","CC","TN","TP","CA"]},"7015":{"coordinates":[103.865946135628,1.33063461006106],"svy21":[31631.1102942107,34760.3552575652],"planningArea":"TP","neighbours":["BS","GL","KL","NV","HG","SG","CC"]},"7016":{"coordinates":[103.941977166932,1.33466313498858],"svy21":[40092.566337104,35206.0519231614],"planningArea":"BD","neighbours":["GL","HG","MP","PL","TM"]},"7017":{"coordinates":[103.875808419206,1.34638285704977],"svy21":[32728.6506901467,36501.732987592],"planningArea":"SG","neighbours":["AM","BS","HG","SE","TP"]},"7019":{"coordinates":[103.902464990999,1.39175222232999],"svy21":[35695.0897383941,41518.5180188008],"planningArea":"SE","neighbours":["AM","PR","HG","PL","PG","SL","SG","YS"]},"7020":{"coordinates":[103.827990076997,1.32305147651579],"svy21":[27406.990938927,33921.8278959282],"planningArea":"NV","neighbours":["BT","KL","CC","TN","TP","CA"]},"7021":{"coordinates":[103.80995114006,1.32006821363365],"svy21":[25399.4342597229,33591.9655932989],"planningArea":"BT","neighbours":["BK","BP","NV","QT","CC","TN","CL"]},"7022":{"coordinates":[103.917638193713,1.30788341871801],"svy21":[37383.9909570105,32244.7789235711],"planningArea":"BD","neighbours":["GL","HG","MP","PL","TM"]},"7023":{"coordinates":[103.822440701914,1.27535177537429],"svy21":[26789.3781794123,28647.4426793642],"planningArea":"BM","neighbours":["QT","TN","SI","CA"]},"7025":{"coordinates":[103.793451108505,1.42656781284688],"svy21":[23563.3395336093,45368.1758330744],"planningArea":"WD","neighbours":["MD","SB","SK"]},"7026":{"coordinates":[103.885120050588,1.35096755912523],"svy21":[33764.9220583513,37008.7061571125],"planningArea":"HG","neighbours":["BD","GL","PL","SE","SG","TP"]},"7027":{"coordinates":[103.890194755287,1.35713595302469],"svy21":[34329.6638843594,37690.7886322979],"planningArea":"HG","neighbours":["BD","GL","PL","SE","SG","TP"]},"7028":{"coordinates":[103.855365171957,1.35007562348323],"svy21":[30453.5388370836,36910.0301692914],"planningArea":"BS","neighbours":["AM","SG","CC","TP"]},"7029":{"coordinates":[103.937608032148,1.34973922385383],"svy21":[39606.2556369361,36873.0704489313],"planningArea":"TM","neighbours":["BD","PR","PL","CH"]},"7030":{"coordinates":[103.783393009829,1.33294800935715],"svy21":[22443.8042111415,35016.1914550979],"planningArea":"BT","neighbours":["BK","BP","NV","QT","CC","TN","CL"]},"7031":{"coordinates":[103.954957944437,1.37434641160383],"svy21":[41536.9732257072,39594.1036771014],"planningArea":"PR","neighbours":["PL","PG","SE","CH","TM"]},"7032":{"coordinates":[103.835772689988,1.31961649151329],"svy21":[28273.1184036601,33542.0043816026],"planningArea":"NV","neighbours":["BT","KL","CC","TN","TP","CA"]},"7101":{"coordinates":[103.941857925437,1.33118040459547],"svy21":[40079.3129556095,34820.9481590763],"planningArea":"BD","neighbours":["GL","HG","MP","PL","TM"]},"7102":{"coordinates":[103.84487466,1.35472295217],"svy21":[29286.06,37423.9],"planningArea":"BS","neighbours":["AM","SG","CC","TP"]},"7104":{"coordinates":[103.891653229373,1.30509154753049],"svy21":[34492.1113962699,31935.985861728],"planningArea":"MP","neighbours":["BD","GL","KL","CA"]},"7105":{"coordinates":[103.837390783121,1.41922603558804],"svy21":[28453.1776143089,44556.3210424408],"planningArea":"YS","neighbours":["AM","MD","SL","SB","SE","CC","SM"]},"7108":{"coordinates":[103.896398814264,1.37154508822264],"svy21":[35020.0627604816,39284.0954767838],"planningArea":"HG","neighbours":["BD","GL","PL","SE","SG","TP"]},"7111":{"coordinates":[103.877880403,1.3413216994],"svy21":[32959.25,35942.1],"planningArea":"TP","neighbours":["BS","GL","KL","NV","HG","SG","CC"]},"7112":{"coordinates":[103.890004423764,1.38879582498401],"svy21":[34308.3992032027,41191.5774543695],"planningArea":"SE","neighbours":["AM","PR","HG","PL","PG","SL","SG","YS"]},"7114":{"coordinates":[103.802420979943,1.33058326666481],"svy21":[24561.4160661083,34754.6755309571],"planningArea":"BT","neighbours":["BK","BP","NV","QT","CC","TN","CL"]},"7118":{"coordinates":[103.834308804,1.37372910038],"svy21":[28110.2,39525.5],"planningArea":"AM","neighbours":["BS","SE","SG","CC","YS"]},"7301":{"coordinates":[103.839753343,1.34027665356],"svy21":[28716.12,35826.5],"planningArea":"TP","neighbours":["BS","GL","KL","NV","HG","SG","CC"]},"7307":{"coordinates":[103.9017199641,1.32747111998672],"svy21":[35612.3792644804,34410.6339794789],"planningArea":"GL","neighbours":["BD","KL","HG","MP","TP"]},"7308":{"coordinates":[103.843149382824,1.38201194250224],"svy21":[29094.0439036535,40441.3768212944],"planningArea":"AM","neighbours":["BS","SE","SG","CC","YS"]},"7309":{"coordinates":[103.784099647149,1.30163374395825],"svy21":[22522.3772030212,31553.617990423],"planningArea":"QT","neighbours":["BM","BT","TN","CL"]},"7310":{"coordinates":[103.956746315713,1.35447463979295],"svy21":[41736.1100740805,37396.7894712463],"planningArea":"TM","neighbours":["BD","PR","PL","CH"]},"7800":{"coordinates":[103.789444793951,1.42641140556345],"svy21":[23117.4954931997,45350.8892124817],"planningArea":"WD","neighbours":["MD","SB","SK"]},"7801":{"coordinates":[103.76936512103,1.30656442170341],"svy21":[20882.5707145296,32098.8640870471],"planningArea":"CL","neighbours":["BK","BT","JE","QT"]},"7802":{"coordinates":[103.848687419363,1.2993648041132],"svy21":[29710.4144953843,31302.6820281148],"planningArea":"CA","neighbours":["BM","KL","MP","NV","TN"]},"7803":{"coordinates":[103.85575955353,1.31910021581673],"svy21":[30497.4603147712,33484.9283776544],"planningArea":"KL","neighbours":["GL","NV","MP","TP","CA"]},"7804":{"coordinates":[103.765959130581,1.36967070432273],"svy21":[20503.7068768963,39076.8485643156],"planningArea":"BP","neighbours":["BK","BT","CC","SK","CK"]},"7805":{"coordinates":[103.774011529322,1.3129281060028],"svy21":[21399.6898938008,32802.5152550172],"planningArea":"QT","neighbours":["BM","BT","TN","CL"]},"7806":{"coordinates":[103.742628105304,1.34311980450764],"svy21":[17907.1336000832,36141.0674422216],"planningArea":"JE","neighbours":["BL","BK","JW","TH","CL","WI"]},"7807":{"coordinates":[103.804100467487,1.43703750789961],"svy21":[24748.4707526183,46525.8443959001],"planningArea":"WD","neighbours":["MD","SB","SK"]},"0701":{"coordinates":[103.804110905425,1.33029291072176],"svy21":[24749.4869699031,34722.567163026],"planningArea":"BT","neighbours":["BK","BP","NV","QT","CC","TN","CL"]},"0702":{"coordinates":[103.935567309385,1.31849283027838],"svy21":[39379.2891936125,33417.9891274609],"planningArea":"BD","neighbours":["GL","HG","MP","PL","TM"]},"0703":{"coordinates":[103.71345906728,1.35048483451872],"svy21":[14660.9717998616,36955.5964394826],"planningArea":"JW","neighbours":["BL","JE","PN","TH","WC"]},"0705":{"coordinates":[103.845760935132,1.37894408046936],"svy21":[29384.6783545623,40102.1495742332],"planningArea":"AM","neighbours":["BS","SE","SG","CC","YS"]},"0706":{"coordinates":[103.919982752561,1.30670176312428],"svy21":[37644.9233144261,32114.1262638159],"planningArea":"BD","neighbours":["GL","HG","MP","PL","TM"]},"0708":{"coordinates":[103.830025340236,1.42426433647651],"svy21":[27633.5108992215,45113.430826623],"planningArea":"YS","neighbours":["AM","MD","SL","SB","SE","CC","SM"]},"0709":{"coordinates":[103.956185936394,1.35728017255863],"svy21":[41673.7303626863,37707.0085183401],"planningArea":"TM","neighbours":["BD","PR","PL","CH"]},"0710":{"coordinates":[103.887038809373,1.36504342002446],"svy21":[33978.4238496535,38565.148383243],"planningArea":"HG","neighbours":["BD","GL","PL","SE","SG","TP"]},"0711":{"coordinates":[103.754374614412,1.3843975859445],"svy21":[19214.5432963278,40705.3131852895],"planningArea":"CK","neighbours":["BK","BP","SK","TH","WC"]},"0712":{"coordinates":[103.936992938728,1.3763338076069],"svy21":[39537.6759528285,39813.7659111302],"planningArea":"PR","neighbours":["PL","PG","SE","CH","TM"]},"0713":{"coordinates":[103.788687862341,1.43030861110897],"svy21":[23033.268532766,45781.824333759],"planningArea":"WD","neighbours":["MD","SB","SK"]},"0802":{"coordinates":[103.835028842354,1.32455605783221],"svy21":[28190.3351049777,34088.1962013785],"planningArea":"NV","neighbours":["BT","KL","CC","TN","TP","CA"]},"0803":{"coordinates":[103.785358436408,1.30304255193393],"svy21":[22662.4720813688,31709.3940755073],"planningArea":"QT","neighbours":["BM","BT","TN","CL"]},"0804":{"coordinates":[103.863576377056,1.33306515740958],"svy21":[31367.377300798,35029.1094067972],"planningArea":"TP","neighbours":["BS","GL","KL","NV","HG","SG","CC"]},"0805":{"coordinates":[103.866498721368,1.35028314949238],"svy21":[31692.5779707199,36932.991401203],"planningArea":"SG","neighbours":["AM","BS","HG","SE","TP"]},"0806":{"coordinates":[103.805704361472,1.32494779287192],"svy21":[24926.8156149369,34131.5293299984],"planningArea":"BT","neighbours":["BK","BP","NV","QT","CC","TN","CL"]},"0908":{"coordinates":[103.741593553753,1.35031929565514],"svy21":[17792.0290890075,36937.1557006724],"planningArea":"BK","neighbours":["BP","BT","JE","TH","CK","CL"]},"0714":{"coordinates":[103.787018608302,1.31352212499743],"svy21":[22847.255549184,32868.1682672426],"planningArea":"QT","neighbours":["BM","BT","TN","CL"]}}