{
	"code": "3063",
	"name": "JURONGVILLE SECONDARY SCHOOL",
	"levels": "S",
	"uen": " T07GS3063D",
	"logo": "./Medias/Images/Schools/logos/tn_3063.jpg",
	"website": "http://www.jurongvillesec.moe.edu.sg",
	"address": "202, JURONG EAST AVENUE 1 ( 609790 )",
	"telephone": [
		"65638704"
	],
	"fax": [
		"65662137"
	],
	"email": "JURONGVILLE@MOE.EDU.SG",
	"mrt": "JURONG EAST MRT, CHINESE GARDEN MRT",
	"bus": "98 , 99 , 157 , 185 , 187 , 198 , 334 , 502 ",
	"GeneralInformation": {
		"Principal": "MDM ONG FEI MIN",
		"Vice Principal": [
			"MDM TAN PEI LEE ELAINE",
			"MR KOH YONG HWEE"
		],
		"School Vision": "Everyone Empowered and Enlightened",
		"School Mission": "To nurture our students into lifelong learners anchored in PRIDE values, to lead and to serve",
		"School Philosophy, Culture and Ethos": [
			"We are guided by our philosophy 'Everyone can Learn, Everyone can Achieve and Everyone can Contribute' in our efforts to nurture our students",
			"to be empowered and enlightened. We offer a student-centric, values-driven education that helps our students to enjoy their school experience",
			"as well as to pursue their passion and interests for life-long learning. Over the years, our students have done well in both the academic and",
			"non-academic domains. Our school community strongly believes in the school motto 'Beyond Self' in leading the school towards achieving our",
			"vision. Our students' success is due to the hard work of a nurturing team of dedicated teachers, supportive parents, alumni and community."
		],
		"Type of School": "GOVERNMENT SCHOOL / CO-ED SCHOOL / SINGLE SESSION",
		"Mother Tongue": "Chinese / Malay / Tamil",
		"Affiliated Schools": "Not Applicable"
	},
	"SubjectOffered": [
		"ADDITIONAL MATHEMATICS",
		"ART",
		"BASIC CHINESE",
		"BASIC MALAY",
		"BASIC TAMIL",
		"BIOLOGY",
		"CHEMISTRY",
		"CHINESE",
		"CHINESE N(A)",
		"CIVICS & MORAL EDUCATION",
		"COMBINED HUMANITIES (S,G)",
		"COMBINED HUMANITIES (S,H)",
		"COMPUTER APPLICATIONS",
		"DESIGN & TECHNOLOGY",
		"ELECTRONICS",
		"ELEMENTS OF BUSINESS SKILLS",
		"ENGLISH LANGUAGE",
		"ENGLISH LANGUAGE (SYLL A)",
		"ENGLISH LANGUAGE (SYLL T)",
		"FOOD & NUTRITION",
		"FOOD AND CONSUMER EDUCATION",
		"GEOGRAPHY",
		"HIGHER CHINESE",
		"HIGHER MALAY",
		"HISTORY",
		"LITERATURE(E)",
		"MALAY",
		"MALAY N(A)",
		"MATHEMATICS",
		"MATHEMATICS (SYLLABUS A)",
		"MATHEMATICS (SYLLABUS T)",
		"MUSIC",
		"PHYSICAL EDUCATION",
		"PHYSICS",
		"PRINCIPLES OF ACCOUNTS",
		"SCIENCE (CHEM, BIO)",
		"SCIENCE (PHY, CHEM)",
		"SCIENCE (SYLL T)",
		"SMART ELECTRICAL TECHNOLOGY",
		"TAMIL",
		"TAMIL N(A)"
	],
	"Cca": {
		"Physical Sports": [
			"Badminton",
			"Basketball",
			"Football",
			"Netball",
			"Sailing",
			"Sepak Takraw",
			"Tchoukball"
		],
		"Uniformed Groups": [
			"Boys' Brigade",
			"Girl Guides",
			"Ncc (Land)",
			"Npcc",
			"Scouts",
			"St. John Brigade"
		],
		"Visual and Performing Arts": [
			"Band - Concert",
			"Choir",
			"Cultural Ensemble - Malay",
			"Dance - Chinese",
			"Dance - Malay",
			"Drama - English",
			"Drumatix Batucada",
			"Orchestra - Chinese"
		],
		"Clubs & Societies": [
			"Infocomm Club"
		]
	},
	"SpecialProgrammes": {
		"MOE Programmes": [
			"Not Available"
		],
		"School Distinctive Programmes": {
			"STEM": "In Heath We Thrive - Connecting the Science and Skills of Health and Wellness",
			"Sports & Outdoor Education": "Sports for Life - Character Education through Sports Exposure, Sports Empowerment and Sports Excellence"
		},
		"Special Student Development Programmes Offered": "At Jurongville Secondary School, we believe in preparing our students for life. The school envisions each student to be a concerned citizen and a"
	},
	"AchievementHistory": {
		"Secondary": {
			"2005": {},
			"2006": {
				"Sports & Games Competition": [
					[
						"",
						"National",
						"National",
						"National",
						"National",
						"Zone",
						"Zone",
						"Zone",
						"Zone"
					],
					[
						"",
						"Boys",
						"Boys",
						"Girls",
						"Girls",
						"Boys",
						"Boys",
						"Girls",
						"Girls"
					],
					[
						"",
						"'B' Div",
						"'C' Div",
						"'B' Div",
						"'C' Div",
						"'B' Div",
						"'C' Div",
						"'B' Div",
						"'C' Div"
					],
					[
						"Soccer",
						"-",
						"-",
						"-",
						"-",
						"-",
						"2nd",
						"-",
						"-"
					]
				],
				"Best Unit Award": {
					"Boys' Brigade": "Silver",
					"Girl Guides": "Silver",
					"Girls' Brigade": "Bronze",
					"Ncc (Land Boys)": "Bronze",
					"Npcc": "Silver",
					"St John Ambulance Brigade": "Silver"
				}
			},
			"2007": {
				"Sports & Games Competition": [
					[
						"",
						"National",
						"National",
						"National",
						"National",
						"Zone",
						"Zone",
						"Zone",
						"Zone"
					],
					[
						"",
						"Boys",
						"Boys",
						"Girls",
						"Girls",
						"Boys",
						"Boys",
						"Girls",
						"Girls"
					],
					[
						"",
						"'B' Div",
						"'C' Div",
						"'B' Div",
						"'C' Div",
						"'B' Div",
						"'C' Div",
						"'B' Div",
						"'C' Div"
					],
					[
						"Sepak Takraw",
						"-",
						"3rd",
						"-",
						"-",
						"4th",
						"2nd",
						"-",
						"-"
					]
				],
				"SYF Central Judging": {
					"Ensemble - Angklung / Kulintang": "Bronze",
					"Orchestra - Chinese": "Bronze",
					"Band - Concert": "Silver",
					"Choir": "Bronze",
					"Dance - Chinese": "Silver",
					"Dance - Malay": "Silver"
				},
				"Best Unit Award": {
					"Ncc (Land Boys)": "Silver",
					"Npcc": "Silver",
					"St John Ambulance Brigade": "Silver",
					"Boys' Brigade": "Bronze"
				}
			},
			"2008": {
				"Sports & Games Competition": [
					[
						"",
						"National",
						"National",
						"National",
						"National",
						"Zone",
						"Zone",
						"Zone",
						"Zone"
					],
					[
						"",
						"Boys",
						"Boys",
						"Girls",
						"Girls",
						"Boys",
						"Boys",
						"Girls",
						"Girls"
					],
					[
						"",
						"'B' Div",
						"'C' Div",
						"'B' Div",
						"'C' Div",
						"'B' Div",
						"'C' Div",
						"'B' Div",
						"'C' Div"
					],
					[
						"Sepak Takraw",
						"4th",
						"-",
						"-",
						"-",
						"1st",
						"1st",
						"-",
						"-"
					],
					[
						"Soccer",
						"-",
						"-",
						"-",
						"-",
						"2nd",
						"2nd",
						"-",
						"-"
					]
				],
				"SYF Central Judging": {
					"Orchestra - Chinese": "Bronze",
					"Band - Concert": "Silver",
					"Choir": "Bronze",
					"Dance - Chinese": "Silver",
					"Dance - Malay": "Silver",
					"Ensemble - Angklung / Kulintang": "Bronze"
				},
				"Best Unit Award": {
					"Girl Guides (Coy 1)": "Bronze",
					"Girls' Brigade": "Bronze",
					"Ncc (Land Boys)": "Silver",
					"Npcc (Land)": "Silver",
					"St John Ambulance Brigade": "Silver",
					"Boys' Brigade": "Silver"
				}
			},
			"2009": {
				"Sports & Games Competition": [
					[
						"",
						"National",
						"National",
						"National",
						"National",
						"Zone",
						"Zone",
						"Zone",
						"Zone"
					],
					[
						"",
						"Boys",
						"Boys",
						"Girls",
						"Girls",
						"Boys",
						"Boys",
						"Girls",
						"Girls"
					],
					[
						"",
						"'B' Div",
						"'C' Div",
						"'B' Div",
						"'C' Div",
						"'B' Div",
						"'C' Div",
						"'B' Div",
						"'C' Div"
					],
					[
						"Sepak Takraw",
						"-",
						"-",
						"-",
						"-",
						"2nd",
						"1st",
						"-",
						"-"
					],
					[
						"Soccer",
						"-",
						"-",
						"-",
						"-",
						"1st",
						"1st",
						"-",
						"-"
					]
				],
				"SYF Central Judging": {
					"Band - Concert": "Silver",
					"Choir": "Bronze",
					"Dance - Chinese": "Silver",
					"Dance - Malay": "Gold",
					"Drama - English": "Silver",
					"Ensemble - Angklung / Kulintang": "Bronze",
					"Orchestra - Chinese": "Bronze"
				},
				"Best Unit Award": {
					"Boys' Brigade": "Silver",
					"Girl Guides (Coy 1)": "Silver",
					"Girls' Brigade": "Bronze",
					"Ncc (Land Boys)": "Silver",
					"Npcc": "Gold",
					"St John Ambulance Brigade": "Silver"
				}
			},
			"2010": {
				"Sports & Games Competition": [
					[
						"",
						"National",
						"National",
						"National",
						"National",
						"Zone",
						"Zone",
						"Zone",
						"Zone"
					],
					[
						"",
						"Boys",
						"Boys",
						"Girls",
						"Girls",
						"Boys",
						"Boys",
						"Girls",
						"Girls"
					],
					[
						"",
						"'B' Div",
						"'C' Div",
						"'B' Div",
						"'C' Div",
						"'B' Div",
						"'C' Div",
						"'B' Div",
						"'C' Div"
					],
					[
						"Sepak Takraw",
						"-",
						"3rd",
						"-",
						"-",
						"1st",
						"3rd",
						"-",
						"-"
					],
					[
						"Soccer",
						"-",
						"-",
						"-",
						"-",
						"1st",
						"1st",
						"-",
						"-"
					]
				],
				"SYF Central Judging": {
					"Band - Concert": "Silver",
					"Choir": "Bronze",
					"Dance - Chinese": "Silver",
					"Dance - Malay": "Gold",
					"Drama - English": "Silver",
					"Ensemble - Angklung / Kulintang": "Bronze",
					"Orchestra - Chinese": "Bronze"
				},
				"Best Unit Award": {
					"Boys' Brigade": "Gold",
					"Girl Guides (Coy 1)": "Silver",
					"Ncc (Land Boys)": "Gold",
					"Npcc (Land)": "Gold",
					"St John Ambulance Brigade": "Gold"
				}
			},
			"2011": {
				"Development Award": [
					"DA (Character Development)",
					"DA (National Education)"
				],
				"Achievement Award": "AA (Academic Value-added) (Special/Express)",
				"Sustained Achievement Award": [
					"SAA (Aesthetics)",
					"SAA (Sports)",
					"SAA (Uniformed Groups)"
				],
				"Sports & Games Competition": [
					[
						"",
						"National",
						"National",
						"National",
						"National",
						"Zone",
						"Zone",
						"Zone",
						"Zone"
					],
					[
						"",
						"Boys",
						"Boys",
						"Girls",
						"Girls",
						"Boys",
						"Boys",
						"Girls",
						"Girls"
					],
					[
						"",
						"'B' Div",
						"'C' Div",
						"'B' Div",
						"'C' Div",
						"'B' Div",
						"'C' Div",
						"'B' Div",
						"'C' Div"
					],
					[
						"Football",
						"2nd",
						"-",
						"-",
						"-",
						"1st",
						"4th",
						"-",
						"-"
					],
					[
						"Sepak Takraw",
						"1st",
						"3rd",
						"-",
						"-",
						"3rd",
						"1st",
						"-",
						"-"
					]
				],
				"SYF Central Judging": {
					"Band - Concert": "Silver",
					"Choir": "Bronze",
					"Dance - Chinese": "Silver",
					"Dance - Malay": "Silver",
					"Drama - English": "Silver",
					"Ensemble - Angklung / Kulintang": "Bronze",
					"Orchestra - Chinese": "Silver"
				},
				"Best Unit Award": {
					"Boys' Brigade": "Gold",
					"Girl Guides (Coy 1)": "Silver",
					"Girls' Brigade": "Silver",
					"Ncc (Land Boys)": "Silver",
					"Npcc (Land)": "Bronze",
					"St John Ambulance Brigade": "Gold"
				}
			},
			"2012": {
				"Development Award": [
					"DA (Character Development)",
					"DA (National Education)"
				],
				"Sustained Achievement Award": [
					"SAA (Aesthetics)",
					"SAA (Sports)",
					"SAA (Uniformed Groups)"
				],
				"Sports & Games Competition": [
					[
						"",
						"National",
						"National",
						"National",
						"National",
						"Zone",
						"Zone",
						"Zone",
						"Zone"
					],
					[
						"",
						"Boys",
						"Boys",
						"Girls",
						"Girls",
						"Boys",
						"Boys",
						"Girls",
						"Girls"
					],
					[
						"",
						"'B' Div",
						"'C' Div",
						"'B' Div",
						"'C' Div",
						"'B' Div",
						"'C' Div",
						"'B' Div",
						"'C' Div"
					],
					[
						"Football",
						"-",
						"3rd",
						"-",
						"-",
						"2nd",
						"3rd",
						"-",
						"-"
					],
					[
						"Sepak Takraw",
						"-",
						"1st",
						"-",
						"-",
						"1st",
						"1st",
						"-",
						"-"
					]
				],
				"SYF Central Judging": {
					"Band - Concert": "Silver",
					"Choir": "Bronze",
					"Dance - Chinese": "Silver",
					"Dance - Malay": "Silver",
					"Drama - English": "Silver",
					"Ensemble - Angklung / Kulintang": "Bronze",
					"Orchestra - Chinese": "Silver"
				},
				"Best Unit Award": {
					"Boys' Brigade": "Gold",
					"Girl Guides (Coy 1)": "Silver",
					"Girls' Brigade": "Silver",
					"Ncc (Land Boys)": "Bronze",
					"Npcc (Land)": "Gold",
					"St John Ambulance Brigade": "Gold"
				}
			},
			"2013": {
				"Development Award": [
					"DA (Character Development)",
					"DA (National Education)"
				],
				"Achievement Award": [
					"AA (Academic Value-added) (Normal)",
					"AA (Academic Value-added) (Special/Express)"
				],
				"Sustained Achievement Award": [
					"SAA (Aesthetics)",
					"SAA (Sports)",
					"SAA (Uniformed Groups)"
				],
				"Sports & Games Competition": [
					[
						"",
						"National",
						"National",
						"National",
						"National",
						"Zone",
						"Zone",
						"Zone",
						"Zone"
					],
					[
						"",
						"Boys",
						"Boys",
						"Girls",
						"Girls",
						"Boys",
						"Boys",
						"Girls",
						"Girls"
					],
					[
						"",
						"'B' Div",
						"'C' Div",
						"'B' Div",
						"'C' Div",
						"'B' Div",
						"'C' Div",
						"'B' Div",
						"'C' Div"
					],
					[
						"Football",
						"-",
						"2nd",
						"-",
						"-",
						"2nd",
						"1st",
						"-",
						"-"
					],
					[
						"Sepak Takraw",
						"-",
						"-",
						"-",
						"-",
						"2nd",
						"1st",
						"-",
						"-"
					]
				],
				"SYF Arts Presentation": {
					"Band - Concert": "Accomplishment",
					"Choir": "Commendation",
					"Dance - Chinese": "Accomplishment",
					"Dance - Malay": "Accomplishment",
					"Drama - English": "Accomplishment",
					"Ensemble - Angklung / Kulintang": "Accomplishment",
					"Orchestra - Chinese": "Accomplishment"
				},
				"Best Unit Award": {
					"Boys' Brigade": "Gold",
					"Girl Guides (Coy 1)": "Silver",
					"Girls' Brigade": "Silver",
					"Ncc (Land Boys)": "Bronze",
					"Npcc (Land)": "Bronze",
					"St John Ambulance Brigade": "Gold"
				}
			},
			"2014": {
				"Development Award": [
					"DA (Character Development)",
					"DA (National Education)"
				],
				"Sports & Games Competition": [
					[
						"",
						"National",
						"National",
						"National",
						"National",
						"Zone",
						"Zone",
						"Zone",
						"Zone"
					],
					[
						"",
						"Boys",
						"Boys",
						"Girls",
						"Girls",
						"Boys",
						"Boys",
						"Girls",
						"Girls"
					],
					[
						"",
						"'B' Div",
						"'C' Div",
						"'B' Div",
						"'C' Div",
						"'B' Div",
						"'C' Div",
						"'B' Div",
						"'C' Div"
					],
					[
						"Football",
						"-",
						"-",
						"-",
						"-",
						"4th",
						"4th",
						"-",
						"-"
					],
					[
						"Sepak Takraw",
						"3rd",
						"2nd",
						"-",
						"-",
						"2nd",
						"2nd",
						"-",
						"-"
					]
				],
				"SYF Arts Presentation": {
					"Band - Concert": "Accomplishment",
					"Choir": "Commendation",
					"Dance - Chinese": "Accomplishment",
					"Dance - Malay": "Accomplishment",
					"Drama - English": "Accomplishment",
					"Ensemble - Angklung / Kulintang": "Accomplishment",
					"Orchestra - Chinese": "Accomplishment"
				},
				"Best Unit Award": {
					"Boys' Brigade": "Gold",
					"Girl Guides (Coy 1)": "Bronze",
					"Girls' Brigade": "Silver",
					"Ncc (Land Boys)": "Bronze",
					"Npcc (Land)": "Bronze",
					"St John Ambulance Brigade": "Gold"
				}
			},
			"2015": {
				"Sports & Games Competition": [
					[
						"",
						"National",
						"National",
						"National",
						"National",
						"Zone",
						"Zone",
						"Zone",
						"Zone"
					],
					[
						"",
						"Boys",
						"Boys",
						"Girls",
						"Girls",
						"Boys",
						"Boys",
						"Girls",
						"Girls"
					],
					[
						"",
						"'B' Div",
						"'C' Div",
						"'B' Div",
						"'C' Div",
						"'B' Div",
						"'C' Div",
						"'B' Div",
						"'C' Div"
					],
					[
						"Football",
						"4th",
						"2nd",
						"-",
						"-",
						"3rd",
						"1st",
						"-",
						"-"
					],
					[
						"Sepak Takraw",
						"-",
						"4th",
						"-",
						"-",
						"2nd",
						"1st",
						"-",
						"-"
					]
				],
				"SYF Arts Presentation": {
					"Band - Concert": "Distinction",
					"Choir": "Accomplishment",
					"Dance - Chinese": "Distinction",
					"Dance - Malay": "Accomplishment",
					"Drama - English": "Distinction",
					"Ensemble - Angklung / Kulintang": "Accomplishment",
					"Orchestra - Chinese": "Accomplishment"
				},
				"Best Unit Award": {
					"Boys' Brigade": "Silver",
					"Girl Guides (Coy 1)": "Bronze",
					"Girls' Brigade": "Silver",
					"Ncc (Land Boys)": "Silver",
					"Npcc (Land)": "Bronze",
					"St John Ambulance Brigade": "Gold"
				}
			},
			"2016": {
				"Sports & Games Competition": [
					[
						"",
						"National",
						"National",
						"National",
						"National",
						"Zone",
						"Zone",
						"Zone",
						"Zone"
					],
					[
						"",
						"Boys",
						"Boys",
						"Girls",
						"Girls",
						"Boys",
						"Boys",
						"Girls",
						"Girls"
					],
					[
						"",
						"'B' Div",
						"'C' Div",
						"'B' Div",
						"'C' Div",
						"'B' Div",
						"'C' Div",
						"'B' Div",
						"'C' Div"
					],
					[
						"Football",
						"-",
						"2nd",
						"-",
						"-",
						"2nd",
						"1st",
						"-",
						"-"
					],
					[
						"Sepak Takraw",
						"-",
						"3rd",
						"-",
						"-",
						"-",
						"-",
						"-",
						"-"
					]
				],
				"SYF Arts Presentation": {
					"Art - Category A": "Recognition",
					"Art - Category B": "Recognition",
					"Band - Concert": "Distinction",
					"Choir": "Accomplishment",
					"Dance - Chinese": "Distinction",
					"Dance - Malay": "Accomplishment",
					"Drama - English": "Distinction",
					"Ensemble - Angklung / Kulintang": "Accomplishment",
					"Orchestra - Chinese": "Accomplishment"
				},
				"Best Unit Award": {
					"Boys' Brigade": "Silver",
					"Girl Guides (Coy 1)": "Gold",
					"Girls' Brigade": "Gold",
					"Ncc (Land Boys)": "Silver",
					"Npcc (Land)": "Bronze",
					"St John Ambulance Brigade": "Gold"
				}
			},
			"2017": {
				"Sports & Games Competition": [
					[
						"",
						"National",
						"National",
						"National",
						"National",
						"Zone",
						"Zone",
						"Zone",
						"Zone"
					],
					[
						"",
						"Boys",
						"Boys",
						"Girls",
						"Girls",
						"Boys",
						"Boys",
						"Girls",
						"Girls"
					],
					[
						"",
						"'B' Div",
						"'C' Div",
						"'B' Div",
						"'C' Div",
						"'B' Div",
						"'C' Div",
						"'B' Div",
						"'C' Div"
					],
					[
						"Football",
						"-",
						"4th",
						"-",
						"-",
						"-",
						"1st",
						"-",
						"-"
					],
					[
						"Sepak Takraw",
						"3rd",
						"4th",
						"-",
						"-",
						"-",
						"-",
						"-",
						"-"
					]
				],
				"SYF Arts Presentation": {
					"Art - Category A": "Recognition",
					"Art - Category B": "Recognition",
					"Band - Concert": "Accomplishment",
					"Chinese Orchestra-Full Orchestra": "Accomplishment",
					"Choir": "Accomplishment",
					"Dance - Chinese": "Distinction",
					"Dance - Malay": "Distinction",
					"Drama - English": "Accomplishment",
					"Ensemble - Angklung / Kulintang": "Distinction"
				},
				"Best Unit Award": {
					"Boys' Brigade": "Silver",
					"Girls' Brigade": "Gold",
					"Ncc (Land Boys)": "Silver",
					"Npcc (Land)": "Silver",
					"St John Ambulance Brigade": "Silver",
					"Girl Guides (Coy 1)": "Gold"
				}
			},
			"2018": {
				"Sports & Games Competition": [
					[
						"",
						"National",
						"National",
						"National",
						"National",
						"Zone",
						"Zone",
						"Zone",
						"Zone"
					],
					[
						"",
						"Boys",
						"Boys",
						"Girls",
						"Girls",
						"Boys",
						"Boys",
						"Girls",
						"Girls"
					],
					[
						"",
						"'B' Div",
						"'C' Div",
						"'B' Div",
						"'C' Div",
						"'B' Div",
						"'C' Div",
						"'B' Div",
						"'C' Div"
					],
					[
						"Sepak Takraw",
						"-",
						"4th",
						"-",
						"-",
						"-",
						"-",
						"-",
						"-"
					],
					[
						"Football",
						"4th",
						"-",
						"-",
						"-",
						"-",
						"4th",
						"-",
						"-"
					]
				],
				"SYF Arts Presentation": {
					"Band - Concert": "Accomplishment",
					"Chinese Orchestra-Full Orchestra": "Accomplishment",
					"Choir": "Accomplishment",
					"Dance - Chinese": "Distinction",
					"Dance - Malay": "Distinction",
					"Drama - English": "Accomplishment",
					"Ensemble - Angklung / Kulintang": "Distinction"
				},
				"Best Unit Award": {
					"Npcc (Land)": "Silver",
					"St John Ambulance Brigade": "Gold",
					"Boys' Brigade": "Gold",
					"Girl Guides": "Gold",
					"Ncc (Land Boys)": "Silver"
				}
			}
		}
	},
	"PsleAggregateHistory": {
		"2005": {
			"Express": [
				"208",
				"229",
				"None-posted"
			],
			"Normal Academic": [
				"155",
				"196",
				"None-posted"
			],
			"Normal Technical": [
				"61",
				"109",
				"None-posted"
			]
		},
		"2006": {
			"Express": [
				"212",
				"231",
				"None-posted"
			],
			"Normal Academic": [
				"164",
				"192",
				"None-posted"
			],
			"Normal Technical": [
				"81",
				"105",
				"None-posted"
			]
		},
		"2007": {
			"Express": [
				"214",
				"229",
				"None-posted"
			],
			"Normal Academic": [
				"162",
				"194",
				"None-posted"
			],
			"Normal Technical": [
				"82",
				"105",
				"None-posted"
			]
		},
		"2008": {
			"Express": [
				"198",
				"231",
				"None-posted"
			],
			"Normal Academic": [
				"168",
				"193",
				"None-posted"
			],
			"Normal Technical": [
				"66",
				"110",
				"None-posted"
			]
		},
		"2009": {
			"Express": [
				"201",
				"228",
				"None-posted"
			],
			"Normal Academic": [
				"163",
				"190",
				"None-posted"
			],
			"Normal Technical": [
				"90",
				"109",
				"None-posted"
			]
		},
		"2010": {
			"Express": [
				"199",
				"222",
				"None-posted"
			],
			"Normal Academic": [
				"162",
				"194",
				"None-posted"
			],
			"Normal Technical": [
				"93",
				"156",
				"None-posted"
			]
		},
		"2011": {
			"Express": [
				"201",
				"225",
				"None-posted"
			],
			"Normal Academic": [
				"160",
				"191",
				"None-posted"
			],
			"Normal Technical": [
				"123",
				"154",
				"None-posted"
			]
		},
		"2012": {
			"Express": [
				"205",
				"234",
				"None-posted"
			],
			"Normal Academic": [
				"169",
				"199",
				"None-posted"
			],
			"Normal Technical": [
				"89",
				"154",
				"None-posted"
			]
		},
		"2013": {
			"Express": [
				"207",
				"233",
				"None-posted"
			],
			"Normal Academic": [
				"170",
				"198",
				"None-posted"
			],
			"Normal Technical": [
				"127",
				"159",
				"None-posted"
			]
		},
		"2014": {
			"Express": [
				"205",
				"247",
				"None-posted"
			],
			"Normal Academic": [
				"171",
				"197",
				"None-posted"
			],
			"Normal Technical": [
				"131",
				"156",
				"None-posted"
			]
		},
		"2015": {
			"Express": [
				"206",
				"229",
				"None-posted"
			],
			"Normal Academic": [
				"152",
				"196",
				"None-posted"
			],
			"Normal Technical": [
				"115",
				"155",
				"None-posted"
			]
		},
		"2016": {
			"Express": [
				"200",
				"230",
				"None-posted"
			],
			"Normal Academic": [
				"164",
				"197",
				"None-posted"
			],
			"Normal Technical": [
				"118",
				"154",
				"None-posted"
			]
		},
		"2017": {
			"Express": [
				"201",
				"225",
				"None-posted"
			],
			"Normal Academic": [
				"164",
				"195",
				"None-posted"
			],
			"Normal Technical": [
				"138",
				"157",
				"None-posted"
			]
		},
		"2018": {
			"Express": [
				"195",
				"231",
				"None-posted"
			],
			"Normal Academic": [
				"161",
				"193",
				"None-posted"
			],
			"Normal Technical": [
				"126",
				"157",
				"None-posted"
			]
		}
	},
	"postalCode": "609790"
}